{
  "config": "{\"version\":\"5.57\",\"themeCollection\":{\"baseTheme\":{\"name\":\"CY24SU08\",\"version\":\"5.58\",\"type\":2},\"customTheme\":{\"name\":\"AccessibleDefault\",\"version\":\"5.58\",\"type\":2}},\"activeSectionIndex\":0,\"bookmarks\":[{\"displayName\":\"1 MENUS CLOSED\",\"name\":\"Bookmark47339036006b5049a547\",\"explorationState\":{\"version\":\"1.3\",\"activeSection\":\"ReportSection\",\"sections\":{\"ReportSection\":{\"visualContainers\":{},\"visualContainerGroups\":{\"9b06cfac3e9c265a59c2\":{\"isHidden\":false},\"ab74578186c02006b149\":{\"isHidden\":true,\"children\":{\"4cd7320eb591e6202e31\":{\"isHidden\":true},\"6765f45fca4376843011\":{\"isHidden\":true},\"89d45d179b3a5240bd4c\":{\"isHidden\":true},\"1e54f65ab30e0783da8b\":{\"isHidden\":true}}},\"0c03f0723683ad88dc08\":{\"isHidden\":false},\"fe6e452737873ed0888a\":{\"isHidden\":true},\"37cb7b2970b5ec94296d\":{\"isHidden\":false},\"c5b84ff90e11e4e09b63\":{\"isHidden\":true},\"fbbba474713d99b45830\":{\"isHidden\":false},\"48b529131e0538427b05\":{\"isHidden\":true},\"b3900526332449a37250\":{\"isHidden\":true}}}},\"objects\":{\"merge\":{\"outspacePane\":[{\"properties\":{\"expanded\":{\"expr\":{\"Literal\":{\"Value\":\"false\"}}}}}]}}},\"options\":{\"targetVisualNames\":[\"b3900526332449a37250\",\"48b529131e0538427b05\",\"c5b84ff90e11e4e09b63\",\"fe6e452737873ed0888a\",\"d7a3da6901e1ba676aa2\",\"59cea7e77de60d550b00\",\"9b0df67436c5ad9d62d5\",\"0cd23d9877a5c0b1c6ed\",\"184ea8f90507474ae602\",\"5d102040c30009313b07\",\"74144c0a3740c35085b5\",\"4018879cd047605a0715\",\"59849e9a8e094d52e3bd\",\"28100e5272a730905093\",\"0fb2f806280970c268b0\",\"3c8170492166a3e21e1a\",\"7afd4ffde1c0101aee09\",\"b124e0140e272d30a0d8\",\"6a0bd8d98b2e38ca5058\",\"c3138c32c291a2728877\",\"b3cff53339dae78e0655\",\"cdd7af757cdea58e6013\",\"c5a43700622da69e0c00\",\"2edd1b068839b6da6354\",\"9da92c1d3658393e3b68\",\"e9d5d2670e9ae00254cb\",\"f1651cce0ad49c12db2c\",\"68352380e07e9a1b693e\",\"e5582f4e745380153ac6\",\"52742ceeae0c3b18959b\",\"fc89fd30920054174007\",\"e2be9ec405d31eeb00c8\"],\"applyOnlyToTargetVisuals\":true,\"suppressData\":true}},{\"displayName\":\"1 OPEN FILTER\",\"name\":\"Bookmark7ba1c88b97db4d557b30\",\"explorationState\":{\"version\":\"1.3\",\"activeSection\":\"ReportSection\",\"sections\":{\"ReportSection\":{\"visualContainers\":{},\"visualContainerGroups\":{\"9b06cfac3e9c265a59c2\":{\"isHidden\":false},\"ab74578186c02006b149\":{\"isHidden\":false,\"children\":{\"4cd7320eb591e6202e31\":{\"isHidden\":true},\"6765f45fca4376843011\":{\"isHidden\":true},\"89d45d179b3a5240bd4c\":{\"isHidden\":true},\"1e54f65ab30e0783da8b\":{\"isHidden\":true}}},\"0c03f0723683ad88dc08\":{\"isHidden\":false},\"fe6e452737873ed0888a\":{\"isHidden\":false},\"37cb7b2970b5ec94296d\":{\"isHidden\":false},\"c5b84ff90e11e4e09b63\":{\"isHidden\":true},\"fbbba474713d99b45830\":{\"isHidden\":false},\"48b529131e0538427b05\":{\"isHidden\":true}}}},\"objects\":{\"merge\":{\"outspacePane\":[{\"properties\":{\"expanded\":{\"expr\":{\"Literal\":{\"Value\":\"false\"}}}}}]}}},\"options\":{\"targetVisualNames\":[\"fe6e452737873ed0888a\",\"c5a43700622da69e0c00\",\"2edd1b068839b6da6354\",\"9da92c1d3658393e3b68\",\"e9d5d2670e9ae00254cb\",\"f1651cce0ad49c12db2c\",\"68352380e07e9a1b693e\",\"e5582f4e745380153ac6\",\"52742ceeae0c3b18959b\",\"fc89fd30920054174007\",\"e2be9ec405d31eeb00c8\"],\"applyOnlyToTargetVisuals\":true,\"suppressData\":true}},{\"displayName\":\"1 OPEN HAMBURGER\",\"name\":\"Bookmarkb90463cc3923b8d1b6eb\",\"explorationState\":{\"version\":\"1.3\",\"activeSection\":\"ReportSection\",\"sections\":{\"ReportSection\":{\"visualContainers\":{},\"visualContainerGroups\":{\"9b06cfac3e9c265a59c2\":{\"isHidden\":false},\"ab74578186c02006b149\":{\"isHidden\":false,\"children\":{\"4cd7320eb591e6202e31\":{\"isHidden\":true},\"6765f45fca4376843011\":{\"isHidden\":true},\"89d45d179b3a5240bd4c\":{\"isHidden\":true},\"1e54f65ab30e0783da8b\":{\"isHidden\":true}}},\"0c03f0723683ad88dc08\":{\"isHidden\":false},\"fe6e452737873ed0888a\":{\"isHidden\":true},\"37cb7b2970b5ec94296d\":{\"isHidden\":false},\"c5b84ff90e11e4e09b63\":{\"isHidden\":true},\"fbbba474713d99b45830\":{\"isHidden\":false},\"48b529131e0538427b05\":{\"isHidden\":false}}}},\"objects\":{\"merge\":{\"outspacePane\":[{\"properties\":{\"expanded\":{\"expr\":{\"Literal\":{\"Value\":\"false\"}}}}}]}}},\"options\":{\"targetVisualNames\":[\"48b529131e0538427b05\",\"184ea8f90507474ae602\",\"5d102040c30009313b07\",\"ab314a9b205097c90c1b\",\"5cecb6c9073d3e166da8\",\"aa4a87ba100220647278\",\"8760b9aad0bec673326b\",\"8fb505eddcc695830c68\",\"d62ad2479bbbece6e78e\",\"4018879cd047605a0715\"],\"applyOnlyToTargetVisuals\":true,\"suppressData\":true}},{\"displayName\":\"2 MENUS CLOSED\",\"name\":\"Bookmark80dac5d7b56d053d0731\",\"explorationState\":{\"version\":\"1.3\",\"activeSection\":\"ReportSectionc632d8da610eec611782\",\"sections\":{\"ReportSectionc632d8da610eec611782\":{\"visualContainers\":{},\"visualContainerGroups\":{\"cfd7ebf065c69383dea2\":{\"isHidden\":false},\"27b89c52b8405048b096\":{\"isHidden\":true},\"88ca4adc170002ad36b7\":{\"isHidden\":false},\"7f261dbfec7008602501\":{\"isHidden\":true},\"b845e700945b07c32e07\":{\"isHidden\":true},\"fd65fd8230aa0786d00c\":{\"isHidden\":false},\"4323606e8b0940911bd2\":{\"isHidden\":false},\"647e8148448842114706\":{\"isHidden\":false},\"3dd88bd3243e1a9407b7\":{\"isHidden\":false,\"children\":{\"71c238a6c982b9b06ac5\":{\"isHidden\":true},\"e84e6441bb13b9804ada\":{\"isHidden\":true},\"b63fcb24967374b1dc16\":{\"isHidden\":true},\"894f5cf779150ae6235c\":{\"isHidden\":true}}}}}},\"objects\":{\"merge\":{\"outspacePane\":[{\"properties\":{\"expanded\":{\"expr\":{\"Literal\":{\"Value\":\"false\"}}}}}]}}},\"options\":{\"targetVisualNames\":[\"27b89c52b8405048b096\",\"7f261dbfec7008602501\",\"b845e700945b07c32e07\",\"a0f9f24c03bd8a040bd9\",\"9024e90e5aec605b4107\",\"6f2860f9048c7c8dd12e\",\"d6b28b120db309a23ea4\",\"6669c4f07d7607677344\",\"1bb77caf519867ece31b\",\"8de4b24a9a8e87b7c0a4\",\"d4e9ea870009e2e99c69\",\"c871ec5c8a279682009e\",\"86514e1de03286a8b904\",\"c9b04c8d835b3e314540\",\"27310a899002e104c35a\",\"85043034b9e7007b248e\",\"9877347788522ba6d80c\",\"16956fd090a0bb41b474\",\"ddca9b5a0920ea175c87\",\"0b71056f07d8944ae5db\",\"102eded18c3dab30ae20\",\"bca25e8d00b6c250ba46\",\"d8c3581e206670a632c6\",\"d70f83e0d1c83c0c874d\",\"fd36e8c24cd109988531\",\"711ca41a306281ce90c5\",\"df9ad220187a45e376a9\",\"c27941403060d2b39062\",\"8b61ec127d880e6e5c30\",\"12135e6eb9d86d0dc2d0\",\"a743c8b05bc98431cb9a\",\"97415b594543d510ea30\"],\"applyOnlyToTargetVisuals\":true,\"suppressData\":true}},{\"displayName\":\"2 OPEN FILTER\",\"name\":\"Bookmarkd3a870a0c955905b9038\",\"explorationState\":{\"version\":\"1.3\",\"activeSection\":\"ReportSectionc632d8da610eec611782\",\"sections\":{\"ReportSectionc632d8da610eec611782\":{\"visualContainers\":{},\"visualContainerGroups\":{\"cfd7ebf065c69383dea2\":{\"isHidden\":false},\"27b89c52b8405048b096\":{\"isHidden\":false},\"88ca4adc170002ad36b7\":{\"isHidden\":false},\"7f261dbfec7008602501\":{\"isHidden\":true},\"b845e700945b07c32e07\":{\"isHidden\":true},\"fd65fd8230aa0786d00c\":{\"isHidden\":false},\"4323606e8b0940911bd2\":{\"isHidden\":false},\"647e8148448842114706\":{\"isHidden\":false},\"3dd88bd3243e1a9407b7\":{\"isHidden\":false,\"children\":{\"71c238a6c982b9b06ac5\":{\"isHidden\":true},\"e84e6441bb13b9804ada\":{\"isHidden\":true},\"b63fcb24967374b1dc16\":{\"isHidden\":true},\"894f5cf779150ae6235c\":{\"isHidden\":true}}}}}},\"objects\":{\"merge\":{\"outspacePane\":[{\"properties\":{\"expanded\":{\"expr\":{\"Literal\":{\"Value\":\"false\"}}}}}]}}},\"options\":{\"targetVisualNames\":[\"27b89c52b8405048b096\",\"a0f9f24c03bd8a040bd9\",\"9024e90e5aec605b4107\",\"6f2860f9048c7c8dd12e\",\"d6b28b120db309a23ea4\",\"6669c4f07d7607677344\",\"1bb77caf519867ece31b\",\"8de4b24a9a8e87b7c0a4\",\"d4e9ea870009e2e99c69\",\"c871ec5c8a279682009e\",\"86514e1de03286a8b904\"],\"applyOnlyToTargetVisuals\":true,\"suppressData\":true}},{\"displayName\":\"2 OPEN HAMBURGER\",\"name\":\"Bookmark638f34addb0940971c90\",\"explorationState\":{\"version\":\"1.3\",\"activeSection\":\"ReportSectionc632d8da610eec611782\",\"sections\":{\"ReportSectionc632d8da610eec611782\":{\"visualContainers\":{},\"visualContainerGroups\":{\"cfd7ebf065c69383dea2\":{\"isHidden\":false},\"27b89c52b8405048b096\":{\"isHidden\":true},\"88ca4adc170002ad36b7\":{\"isHidden\":false},\"7f261dbfec7008602501\":{\"isHidden\":true},\"b845e700945b07c32e07\":{\"isHidden\":false},\"fd65fd8230aa0786d00c\":{\"isHidden\":false},\"4323606e8b0940911bd2\":{\"isHidden\":false},\"647e8148448842114706\":{\"isHidden\":false},\"3dd88bd3243e1a9407b7\":{\"isHidden\":false,\"children\":{\"71c238a6c982b9b06ac5\":{\"isHidden\":true},\"e84e6441bb13b9804ada\":{\"isHidden\":true},\"b63fcb24967374b1dc16\":{\"isHidden\":true},\"894f5cf779150ae6235c\":{\"isHidden\":true}}}}}},\"objects\":{\"merge\":{\"outspacePane\":[{\"properties\":{\"expanded\":{\"expr\":{\"Literal\":{\"Value\":\"false\"}}}}}]}}},\"options\":{\"targetVisualNames\":[\"b845e700945b07c32e07\",\"d70f83e0d1c83c0c874d\",\"fd36e8c24cd109988531\",\"711ca41a306281ce90c5\",\"df9ad220187a45e376a9\",\"c27941403060d2b39062\",\"8b61ec127d880e6e5c30\",\"12135e6eb9d86d0dc2d0\",\"a743c8b05bc98431cb9a\",\"97415b594543d510ea30\"],\"applyOnlyToTargetVisuals\":true,\"suppressData\":true}},{\"displayName\":\"3 MENUS CLOSED\",\"name\":\"Bookmark9ff6182dcc55c6d0179c\",\"explorationState\":{\"version\":\"1.3\",\"activeSection\":\"ReportSectionc80c3e5168ba660db02b\",\"sections\":{\"ReportSectionc80c3e5168ba660db02b\":{\"visualContainers\":{},\"visualContainerGroups\":{\"4622f336a1e40806576a\":{\"isHidden\":false},\"2cba5585291c67b1731a\":{\"isHidden\":true},\"5664f680a1dce77e45d3\":{\"isHidden\":false},\"d530aa819e0d00e95e13\":{\"isHidden\":true},\"436efbdf65d2c18e986a\":{\"isHidden\":true},\"e6a3afd46388c2e7ca64\":{\"isHidden\":false},\"7bf544c8de58e2dbca5e\":{\"isHidden\":false},\"35f62d2a95739ace0800\":{\"isHidden\":false},\"298a15e805ecda05a5e7\":{\"isHidden\":false},\"2811b415c1a7a577a889\":{\"isHidden\":false,\"children\":{\"92152becbc8aa20d2976\":{\"isHidden\":true},\"ebb096c63e809a81737d\":{\"isHidden\":true},\"55fd5ffbd139d17d6759\":{\"isHidden\":true},\"32a25b04a84e017318cd\":{\"isHidden\":true}}}}}},\"objects\":{\"merge\":{\"outspacePane\":[{\"properties\":{\"expanded\":{\"expr\":{\"Literal\":{\"Value\":\"false\"}}}}}]}}},\"options\":{\"targetVisualNames\":[\"2cba5585291c67b1731a\",\"d530aa819e0d00e95e13\",\"436efbdf65d2c18e986a\",\"0e28b01eb6e2e90a32b1\",\"c7800b23c9229b007c83\",\"cc03821eaaa8367e6354\",\"0772cd8c47b0b3808542\",\"b3a8587e036e00384828\",\"6fc6556ae81b4913d658\",\"972f7a7d709ece0eb055\",\"1f8537aa49ea71117c53\",\"36ba7d1247ccd6870059\",\"176ced27d58008c31503\",\"470d65a78a70e1078937\",\"f84241d9d1b1dba20635\",\"a21cef4a419a2b7c09e0\",\"4ef26778c42773721acb\",\"6455ade483a6804d8de0\",\"e7cdac974c9061e3a929\",\"1cbe9f607a6367480eb1\",\"e7d418f7984a096ad185\",\"bec488d705c082697e4e\",\"b33950514457d763b698\",\"6a18b6602c7d1326be26\",\"cdc9223c143971e5da0a\",\"929bbef5c77e7cec7709\",\"6ad22d84407b70711119\",\"1d2aa4b8eb35c02d90a3\",\"17e59e9a5e4753e1dc64\",\"9a65dc050554a0cb913b\",\"0b23a8a2575670dbd5bb\",\"f8d9f27cc18ec3b04aa0\"],\"applyOnlyToTargetVisuals\":true,\"suppressData\":true}},{\"displayName\":\"3 OPEN FILTER\",\"name\":\"Bookmarkd41da4f0aa5288e95679\",\"explorationState\":{\"version\":\"1.3\",\"activeSection\":\"ReportSectionc80c3e5168ba660db02b\",\"sections\":{\"ReportSectionc80c3e5168ba660db02b\":{\"visualContainers\":{},\"visualContainerGroups\":{\"4622f336a1e40806576a\":{\"isHidden\":false},\"2cba5585291c67b1731a\":{\"isHidden\":false},\"5664f680a1dce77e45d3\":{\"isHidden\":false},\"d530aa819e0d00e95e13\":{\"isHidden\":true},\"436efbdf65d2c18e986a\":{\"isHidden\":true},\"e6a3afd46388c2e7ca64\":{\"isHidden\":false},\"7bf544c8de58e2dbca5e\":{\"isHidden\":false},\"35f62d2a95739ace0800\":{\"isHidden\":false},\"298a15e805ecda05a5e7\":{\"isHidden\":false},\"2811b415c1a7a577a889\":{\"isHidden\":false,\"children\":{\"92152becbc8aa20d2976\":{\"isHidden\":true},\"ebb096c63e809a81737d\":{\"isHidden\":true},\"55fd5ffbd139d17d6759\":{\"isHidden\":true},\"32a25b04a84e017318cd\":{\"isHidden\":true}}}}}},\"objects\":{\"merge\":{\"outspacePane\":[{\"properties\":{\"expanded\":{\"expr\":{\"Literal\":{\"Value\":\"false\"}}}}}]}}},\"options\":{\"targetVisualNames\":[\"2cba5585291c67b1731a\",\"0e28b01eb6e2e90a32b1\",\"c7800b23c9229b007c83\",\"cc03821eaaa8367e6354\",\"0772cd8c47b0b3808542\",\"b3a8587e036e00384828\",\"6fc6556ae81b4913d658\",\"972f7a7d709ece0eb055\",\"1f8537aa49ea71117c53\",\"36ba7d1247ccd6870059\",\"176ced27d58008c31503\"],\"applyOnlyToTargetVisuals\":true,\"suppressData\":true}},{\"displayName\":\"3 OPEN HAMBURGER\",\"name\":\"Bookmark1c4a2d7cb2cc821a8007\",\"explorationState\":{\"version\":\"1.3\",\"activeSection\":\"ReportSectionc80c3e5168ba660db02b\",\"sections\":{\"ReportSectionc80c3e5168ba660db02b\":{\"visualContainers\":{},\"visualContainerGroups\":{\"4622f336a1e40806576a\":{\"isHidden\":false},\"2cba5585291c67b1731a\":{\"isHidden\":true},\"5664f680a1dce77e45d3\":{\"isHidden\":false},\"d530aa819e0d00e95e13\":{\"isHidden\":true},\"436efbdf65d2c18e986a\":{\"isHidden\":false},\"e6a3afd46388c2e7ca64\":{\"isHidden\":false},\"7bf544c8de58e2dbca5e\":{\"isHidden\":false},\"35f62d2a95739ace0800\":{\"isHidden\":false},\"298a15e805ecda05a5e7\":{\"isHidden\":false},\"2811b415c1a7a577a889\":{\"isHidden\":false,\"children\":{\"92152becbc8aa20d2976\":{\"isHidden\":true},\"ebb096c63e809a81737d\":{\"isHidden\":true},\"55fd5ffbd139d17d6759\":{\"isHidden\":true},\"32a25b04a84e017318cd\":{\"isHidden\":true}}}}}},\"objects\":{\"merge\":{\"outspacePane\":[{\"properties\":{\"expanded\":{\"expr\":{\"Literal\":{\"Value\":\"false\"}}}}}]}}},\"options\":{\"targetVisualNames\":[\"436efbdf65d2c18e986a\",\"6a18b6602c7d1326be26\",\"cdc9223c143971e5da0a\",\"929bbef5c77e7cec7709\",\"6ad22d84407b70711119\",\"1d2aa4b8eb35c02d90a3\",\"17e59e9a5e4753e1dc64\",\"9a65dc050554a0cb913b\",\"0b23a8a2575670dbd5bb\",\"f8d9f27cc18ec3b04aa0\"],\"applyOnlyToTargetVisuals\":true,\"suppressData\":true}},{\"displayName\":\"4 MENUS CLOSED\",\"name\":\"Bookmarkaeb717c8b860990b8574\",\"explorationState\":{\"version\":\"1.3\",\"activeSection\":\"ReportSectionf93b1f7a7303e3032711\",\"sections\":{\"ReportSectionf93b1f7a7303e3032711\":{\"visualContainers\":{},\"visualContainerGroups\":{\"3387f98c33a162cbec07\":{\"isHidden\":false},\"e68bd798d0eab9e409ab\":{\"isHidden\":true},\"3246a1eac3dc2b91042e\":{\"isHidden\":false},\"2a5085e2686682ed5e9e\":{\"isHidden\":true},\"11d19f3f986d4da917dc\":{\"isHidden\":true},\"22d6724b7e86d0cb0425\":{\"isHidden\":false},\"60860078a33061a8b200\":{\"isHidden\":false},\"0c02026a0caaa21b4bc5\":{\"isHidden\":false},\"a51b2e5bb56c077d9e08\":{\"isHidden\":false},\"ab9ec3d0698442c2c629\":{\"isHidden\":false},\"feeb7d941d1a28a76db3\":{\"isHidden\":false,\"children\":{\"025ba2d3230d55be2e95\":{\"isHidden\":true},\"23e11fc71ab0b804b222\":{\"isHidden\":false},\"24b63192a8bcab070e00\":{\"isHidden\":true},\"94ca1930c0738a064e47\":{\"isHidden\":true}}}}}},\"objects\":{\"merge\":{\"outspacePane\":[{\"properties\":{\"expanded\":{\"expr\":{\"Literal\":{\"Value\":\"false\"}}}}}]}}},\"options\":{\"targetVisualNames\":[\"e68bd798d0eab9e409ab\",\"2a5085e2686682ed5e9e\",\"11d19f3f986d4da917dc\",\"b74d6ddae42d2d20931d\",\"43988de7ec07e00720c0\",\"e6b8583004c5c57c14e4\",\"78c0fb88099b4793ec04\",\"006a0d7d0a08029621d3\",\"47b563c45e2197083224\",\"6e6ffce800578e274069\",\"0babb2410c4e18b1190d\",\"df4040ca090c7ee1386e\",\"43941864a92900b9c654\",\"c99a2f461b289d6745d7\",\"f6c58bf191343856dd12\",\"a58d28b20d7085e0c40e\",\"05893f22775d320d0b7d\",\"374f7cc14080c007ec66\",\"9bd2c0dd962d1db3c18b\",\"d87908aaad860de2170e\",\"b9e636d93ba8330148e2\",\"ef4df8fe95082edae358\",\"939b41200d0abc7a0a1b\",\"bcacb407c60ad5655809\",\"24561fbd00da00aae57d\",\"ca6a269ced1acb207030\",\"ecbdb685b083c403ae0d\",\"8f8567e560e7d060d935\",\"93cd0ba7d5eba0e3adaa\",\"76d92ca5a8714a605228\",\"27b16560dec85eadb2d7\",\"f4149ede9e478d1131eb\"],\"applyOnlyToTargetVisuals\":true,\"suppressData\":true}},{\"displayName\":\"4 OPEN FILTER\",\"name\":\"Bookmarke35c5e0671297aa3b7da\",\"explorationState\":{\"version\":\"1.3\",\"activeSection\":\"ReportSectionf93b1f7a7303e3032711\",\"sections\":{\"ReportSectionf93b1f7a7303e3032711\":{\"visualContainers\":{},\"visualContainerGroups\":{\"3387f98c33a162cbec07\":{\"isHidden\":false},\"e68bd798d0eab9e409ab\":{\"isHidden\":false},\"3246a1eac3dc2b91042e\":{\"isHidden\":false},\"2a5085e2686682ed5e9e\":{\"isHidden\":true},\"11d19f3f986d4da917dc\":{\"isHidden\":true},\"22d6724b7e86d0cb0425\":{\"isHidden\":false},\"60860078a33061a8b200\":{\"isHidden\":false},\"0c02026a0caaa21b4bc5\":{\"isHidden\":false},\"a51b2e5bb56c077d9e08\":{\"isHidden\":false},\"ab9ec3d0698442c2c629\":{\"isHidden\":false},\"feeb7d941d1a28a76db3\":{\"isHidden\":false,\"children\":{\"025ba2d3230d55be2e95\":{\"isHidden\":true},\"23e11fc71ab0b804b222\":{\"isHidden\":false},\"24b63192a8bcab070e00\":{\"isHidden\":true},\"94ca1930c0738a064e47\":{\"isHidden\":true}}}}}},\"objects\":{\"merge\":{\"outspacePane\":[{\"properties\":{\"expanded\":{\"expr\":{\"Literal\":{\"Value\":\"false\"}}}}}]}}},\"options\":{\"targetVisualNames\":[\"e68bd798d0eab9e409ab\",\"b74d6ddae42d2d20931d\",\"43988de7ec07e00720c0\",\"e6b8583004c5c57c14e4\",\"78c0fb88099b4793ec04\",\"006a0d7d0a08029621d3\",\"47b563c45e2197083224\",\"6e6ffce800578e274069\",\"0babb2410c4e18b1190d\",\"df4040ca090c7ee1386e\",\"43941864a92900b9c654\"],\"applyOnlyToTargetVisuals\":true,\"suppressData\":true}},{\"displayName\":\"4 OPEN HAMBURGER\",\"name\":\"Bookmark6261d50f28965a019421\",\"explorationState\":{\"version\":\"1.3\",\"activeSection\":\"ReportSectionf93b1f7a7303e3032711\",\"sections\":{\"ReportSectionf93b1f7a7303e3032711\":{\"visualContainers\":{},\"visualContainerGroups\":{\"3387f98c33a162cbec07\":{\"isHidden\":false},\"e68bd798d0eab9e409ab\":{\"isHidden\":true},\"3246a1eac3dc2b91042e\":{\"isHidden\":false},\"2a5085e2686682ed5e9e\":{\"isHidden\":true},\"11d19f3f986d4da917dc\":{\"isHidden\":false},\"22d6724b7e86d0cb0425\":{\"isHidden\":false},\"60860078a33061a8b200\":{\"isHidden\":false},\"0c02026a0caaa21b4bc5\":{\"isHidden\":false},\"a51b2e5bb56c077d9e08\":{\"isHidden\":false},\"ab9ec3d0698442c2c629\":{\"isHidden\":false},\"feeb7d941d1a28a76db3\":{\"isHidden\":false,\"children\":{\"025ba2d3230d55be2e95\":{\"isHidden\":true},\"23e11fc71ab0b804b222\":{\"isHidden\":false},\"24b63192a8bcab070e00\":{\"isHidden\":true},\"94ca1930c0738a064e47\":{\"isHidden\":true}}}}}},\"objects\":{\"merge\":{\"outspacePane\":[{\"properties\":{\"expanded\":{\"expr\":{\"Literal\":{\"Value\":\"false\"}}}}}]}}},\"options\":{\"targetVisualNames\":[\"11d19f3f986d4da917dc\",\"bcacb407c60ad5655809\",\"24561fbd00da00aae57d\",\"ca6a269ced1acb207030\",\"ecbdb685b083c403ae0d\",\"8f8567e560e7d060d935\",\"93cd0ba7d5eba0e3adaa\",\"76d92ca5a8714a605228\",\"27b16560dec85eadb2d7\",\"f4149ede9e478d1131eb\"],\"applyOnlyToTargetVisuals\":true,\"suppressData\":true}},{\"displayName\":\"5 MENUS CLOSED\",\"name\":\"Bookmarka0010f7406536760b2e0\",\"explorationState\":{\"version\":\"1.3\",\"activeSection\":\"ReportSectione5824476c4c5a02e072e\",\"sections\":{\"ReportSectione5824476c4c5a02e072e\":{\"visualContainers\":{},\"visualContainerGroups\":{\"8f71a014ce059ea38965\":{\"isHidden\":false},\"1bac64e6dd645e42e33c\":{\"isHidden\":true},\"a23782b02820e0088d3a\":{\"isHidden\":false},\"4865e7178088d870c4a2\":{\"isHidden\":true},\"c46d29aa47d4ab03bec3\":{\"isHidden\":true},\"b3fa7f3c340779134c07\":{\"isHidden\":false},\"0f0c34a483d289723203\":{\"isHidden\":false},\"2713088803ba566a313b\":{\"isHidden\":false},\"fcfb3e881eb2ca92c447\":{\"isHidden\":false},\"91fb17dfe49d30c68910\":{\"isHidden\":false},\"b55855329aaa923bad03\":{\"isHidden\":false},\"c48b5ecf9c3b1d9c581a\":{\"isHidden\":false,\"children\":{\"0fa7e08747640010ae74\":{\"isHidden\":true},\"e82b9c6ec30d3cb3a15b\":{\"isHidden\":true},\"352f16d29dc9705378a1\":{\"isHidden\":true},\"37cf8aaf4d80768cadc0\":{\"isHidden\":true}}}}}},\"objects\":{\"merge\":{\"outspacePane\":[{\"properties\":{\"expanded\":{\"expr\":{\"Literal\":{\"Value\":\"false\"}}}}}]}}},\"options\":{\"targetVisualNames\":[\"1bac64e6dd645e42e33c\",\"4865e7178088d870c4a2\",\"c46d29aa47d4ab03bec3\",\"04d20a1eb70409700244\",\"7fe69a35062323701c79\",\"b5a704ad1b209b4e9060\",\"e3b80e999a90060c3652\",\"6485df928355d05ed3cd\",\"678ab6241654e20302dc\",\"3cd1826380e3b48e04b6\",\"88d0bd040e030b3b7939\",\"35016ac6860078988e23\",\"89ee653e0608b48d0a2a\",\"886fd824015badce904e\",\"ad1ccc8055cbcd0cbc2c\",\"dd9c68c38a1150db069b\",\"b33529b0056cce00d101\",\"1c2ac15722e4e5260aaa\",\"751a9db692909907da0d\",\"ef60b6b0775b4b730548\",\"f8cd6451a2ad04632ae4\",\"40df55d5243302045eb7\",\"640181263c16a0b87332\",\"07e4c9fd5b06a272d502\",\"d8528cfc8ae8cc1be26c\",\"f8361ea2a313069d05c1\",\"ed25c9635cdd8ac19a1c\",\"c43def630b38e16eaa97\",\"388cf27695105e304150\",\"c66abaff12ab00a45c1a\",\"60c7527570e04092110d\",\"e0ac0c560060b22049e0\"],\"applyOnlyToTargetVisuals\":true,\"suppressData\":true}},{\"displayName\":\"5 OPEN FILTER\",\"name\":\"Bookmarkc13b5408d0b6d029b478\",\"explorationState\":{\"version\":\"1.3\",\"activeSection\":\"ReportSectione5824476c4c5a02e072e\",\"sections\":{\"ReportSectione5824476c4c5a02e072e\":{\"visualContainers\":{},\"visualContainerGroups\":{\"8f71a014ce059ea38965\":{\"isHidden\":false},\"1bac64e6dd645e42e33c\":{\"isHidden\":false},\"a23782b02820e0088d3a\":{\"isHidden\":false},\"4865e7178088d870c4a2\":{\"isHidden\":true},\"c46d29aa47d4ab03bec3\":{\"isHidden\":true},\"b3fa7f3c340779134c07\":{\"isHidden\":false},\"0f0c34a483d289723203\":{\"isHidden\":false},\"2713088803ba566a313b\":{\"isHidden\":false},\"fcfb3e881eb2ca92c447\":{\"isHidden\":false},\"91fb17dfe49d30c68910\":{\"isHidden\":false},\"b55855329aaa923bad03\":{\"isHidden\":false},\"c48b5ecf9c3b1d9c581a\":{\"isHidden\":false,\"children\":{\"0fa7e08747640010ae74\":{\"isHidden\":true},\"e82b9c6ec30d3cb3a15b\":{\"isHidden\":true},\"352f16d29dc9705378a1\":{\"isHidden\":true},\"37cf8aaf4d80768cadc0\":{\"isHidden\":true}}}}}},\"objects\":{\"merge\":{\"outspacePane\":[{\"properties\":{\"expanded\":{\"expr\":{\"Literal\":{\"Value\":\"false\"}}}}}]}}},\"options\":{\"targetVisualNames\":[\"1bac64e6dd645e42e33c\",\"04d20a1eb70409700244\",\"7fe69a35062323701c79\",\"b5a704ad1b209b4e9060\",\"e3b80e999a90060c3652\",\"6485df928355d05ed3cd\",\"678ab6241654e20302dc\",\"3cd1826380e3b48e04b6\",\"88d0bd040e030b3b7939\",\"35016ac6860078988e23\",\"89ee653e0608b48d0a2a\"],\"applyOnlyToTargetVisuals\":true,\"suppressData\":true}},{\"displayName\":\"5 OPEN HAMBURGER\",\"name\":\"Bookmark8c0b3da64129be0e6b3a\",\"explorationState\":{\"version\":\"1.3\",\"activeSection\":\"ReportSectione5824476c4c5a02e072e\",\"sections\":{\"ReportSectione5824476c4c5a02e072e\":{\"visualContainers\":{},\"visualContainerGroups\":{\"8f71a014ce059ea38965\":{\"isHidden\":false},\"1bac64e6dd645e42e33c\":{\"isHidden\":true},\"a23782b02820e0088d3a\":{\"isHidden\":false},\"4865e7178088d870c4a2\":{\"isHidden\":true},\"c46d29aa47d4ab03bec3\":{\"isHidden\":false},\"b3fa7f3c340779134c07\":{\"isHidden\":false},\"0f0c34a483d289723203\":{\"isHidden\":false},\"2713088803ba566a313b\":{\"isHidden\":false},\"fcfb3e881eb2ca92c447\":{\"isHidden\":false},\"91fb17dfe49d30c68910\":{\"isHidden\":false},\"b55855329aaa923bad03\":{\"isHidden\":false},\"c48b5ecf9c3b1d9c581a\":{\"isHidden\":false,\"children\":{\"0fa7e08747640010ae74\":{\"isHidden\":true},\"e82b9c6ec30d3cb3a15b\":{\"isHidden\":true},\"352f16d29dc9705378a1\":{\"isHidden\":true},\"37cf8aaf4d80768cadc0\":{\"isHidden\":true}}}}}},\"objects\":{\"merge\":{\"outspacePane\":[{\"properties\":{\"expanded\":{\"expr\":{\"Literal\":{\"Value\":\"false\"}}}}}]}}},\"options\":{\"targetVisualNames\":[\"c46d29aa47d4ab03bec3\",\"07e4c9fd5b06a272d502\",\"d8528cfc8ae8cc1be26c\",\"f8361ea2a313069d05c1\",\"ed25c9635cdd8ac19a1c\",\"c43def630b38e16eaa97\",\"388cf27695105e304150\",\"c66abaff12ab00a45c1a\",\"60c7527570e04092110d\",\"e0ac0c560060b22049e0\"],\"applyOnlyToTargetVisuals\":true,\"suppressData\":true}},{\"displayName\":\"6 MENUS CLOSED\",\"name\":\"Bookmark0a7af5700e55d45a04e2\",\"explorationState\":{\"version\":\"1.3\",\"activeSection\":\"ReportSection384694c8a1b41a968c27\",\"sections\":{\"ReportSection384694c8a1b41a968c27\":{\"visualContainers\":{},\"visualContainerGroups\":{\"3f8070d84cad08986d50\":{\"isHidden\":false},\"cecb0d3430c165208340\":{\"isHidden\":true},\"25afc28c016bcc7e690b\":{\"isHidden\":false},\"b900118a052a6383ead9\":{\"isHidden\":true},\"ebaead4dd00761ad5a9a\":{\"isHidden\":true},\"1bfa0f5351d97258d38b\":{\"isHidden\":false,\"children\":{\"49ddfbe6c61e8c27ec75\":{\"isHidden\":true},\"9ae4518e6e29857cb325\":{\"isHidden\":true},\"ee528863a0c51b2da3b0\":{\"isHidden\":true},\"b2af9d4549ab045edb09\":{\"isHidden\":true}}}}}},\"objects\":{\"merge\":{\"outspacePane\":[{\"properties\":{\"expanded\":{\"expr\":{\"Literal\":{\"Value\":\"false\"}}}}}]}}},\"options\":{\"targetVisualNames\":[\"cecb0d3430c165208340\",\"b900118a052a6383ead9\",\"ebaead4dd00761ad5a9a\",\"20b14700dbe03db66631\",\"27b1dad6415303105506\",\"cd4ea50c4a006ec7d03e\",\"eeeebeccd32024200d7a\",\"73af8c403e6c2c4e9603\",\"6decfbf08228e93a5b67\",\"8b686996e8c89c74a37a\",\"c48ab635c80cc7b4eda8\",\"65c340507c5aa5785d35\",\"29a26bf252e7746e6c40\",\"8bd7d0366641d1c09d07\",\"23d1e7a00e4404b8c0c0\",\"3d66f02830102a918a32\",\"5e182b17dc943dad0010\",\"28d76914a3b2a69ecebc\",\"62f0a2f00629cc00ccb9\",\"11872de76c409d87673b\",\"93853b3e945106739640\",\"15f75ef1224368dece96\",\"400de6a7d66b616bc77a\",\"c34929e183eeb336a95d\",\"7698f3c797791e6783da\",\"2de96db7a08d04ce0686\",\"0ba10a75dd7c92a7441e\",\"fc8290be562816b8d006\",\"f48b15286e60b6585664\",\"19c6351906a630d2400c\",\"aa522ac11a0d08dd4460\",\"22e4a73e26ad287261c1\"],\"applyOnlyToTargetVisuals\":true,\"suppressData\":true}},{\"displayName\":\"6 OPEN FILTER\",\"name\":\"Bookmark1587d690c36ae0ec3461\",\"explorationState\":{\"version\":\"1.3\",\"activeSection\":\"ReportSection384694c8a1b41a968c27\",\"sections\":{\"ReportSection384694c8a1b41a968c27\":{\"visualContainers\":{},\"visualContainerGroups\":{\"3f8070d84cad08986d50\":{\"isHidden\":false},\"cecb0d3430c165208340\":{\"isHidden\":false},\"25afc28c016bcc7e690b\":{\"isHidden\":false},\"b900118a052a6383ead9\":{\"isHidden\":true},\"ebaead4dd00761ad5a9a\":{\"isHidden\":true},\"1bfa0f5351d97258d38b\":{\"isHidden\":false,\"children\":{\"49ddfbe6c61e8c27ec75\":{\"isHidden\":true},\"9ae4518e6e29857cb325\":{\"isHidden\":true},\"ee528863a0c51b2da3b0\":{\"isHidden\":true},\"b2af9d4549ab045edb09\":{\"isHidden\":true}}}}}},\"objects\":{\"merge\":{\"outspacePane\":[{\"properties\":{\"expanded\":{\"expr\":{\"Literal\":{\"Value\":\"false\"}}}}}]}}},\"options\":{\"targetVisualNames\":[\"cecb0d3430c165208340\",\"20b14700dbe03db66631\",\"27b1dad6415303105506\",\"cd4ea50c4a006ec7d03e\",\"eeeebeccd32024200d7a\",\"73af8c403e6c2c4e9603\",\"6decfbf08228e93a5b67\",\"8b686996e8c89c74a37a\",\"c48ab635c80cc7b4eda8\",\"65c340507c5aa5785d35\",\"29a26bf252e7746e6c40\"],\"applyOnlyToTargetVisuals\":true,\"suppressData\":true}},{\"displayName\":\"6 OPEN HAMBURGER\",\"name\":\"Bookmark6909e9bcb6be90101126\",\"explorationState\":{\"version\":\"1.3\",\"activeSection\":\"ReportSection384694c8a1b41a968c27\",\"sections\":{\"ReportSection384694c8a1b41a968c27\":{\"visualContainers\":{},\"visualContainerGroups\":{\"3f8070d84cad08986d50\":{\"isHidden\":false},\"cecb0d3430c165208340\":{\"isHidden\":true},\"25afc28c016bcc7e690b\":{\"isHidden\":false},\"b900118a052a6383ead9\":{\"isHidden\":true},\"ebaead4dd00761ad5a9a\":{\"isHidden\":false},\"1bfa0f5351d97258d38b\":{\"isHidden\":false,\"children\":{\"49ddfbe6c61e8c27ec75\":{\"isHidden\":true},\"9ae4518e6e29857cb325\":{\"isHidden\":true},\"ee528863a0c51b2da3b0\":{\"isHidden\":true},\"b2af9d4549ab045edb09\":{\"isHidden\":true}}}}}},\"objects\":{\"merge\":{\"outspacePane\":[{\"properties\":{\"expanded\":{\"expr\":{\"Literal\":{\"Value\":\"false\"}}}}}]}}},\"options\":{\"targetVisualNames\":[\"ebaead4dd00761ad5a9a\",\"c34929e183eeb336a95d\",\"7698f3c797791e6783da\",\"2de96db7a08d04ce0686\",\"0ba10a75dd7c92a7441e\",\"fc8290be562816b8d006\",\"f48b15286e60b6585664\",\"19c6351906a630d2400c\",\"aa522ac11a0d08dd4460\",\"22e4a73e26ad287261c1\"],\"applyOnlyToTargetVisuals\":true,\"suppressData\":true}},{\"displayName\":\"D INFO SNAPSHOTS\",\"name\":\"Bookmark60cda9ab071b0963059b\",\"explorationState\":{\"version\":\"1.3\",\"activeSection\":\"ReportSectionb63c0964e356021e695b\",\"sections\":{\"ReportSectionb63c0964e356021e695b\":{\"visualContainers\":{},\"visualContainerGroups\":{\"1eaaa2786b7c756951b7\":{\"isHidden\":false},\"00022aa0d3e28320a4ea\":{\"isHidden\":true},\"db663f47ca3cce960626\":{\"isHidden\":false},\"d6d2061e3a8472928e09\":{\"isHidden\":true},\"068f08d285909b5931b3\":{\"isHidden\":true},\"8320bb2036a8eee40565\":{\"isHidden\":false},\"e6b402353da657b951b1\":{\"isHidden\":true},\"0516d87aad04d462220e\":{\"isHidden\":true}}}},\"objects\":{\"merge\":{\"outspacePane\":[{\"properties\":{\"expanded\":{\"expr\":{\"Literal\":{\"Value\":\"false\"}}}}}]}}},\"options\":{\"targetVisualNames\":[\"0516d87aad04d462220e\",\"e6b402353da657b951b1\",\"8320bb2036a8eee40565\",\"0c359ecf40e85e20c940\",\"19d8b8d0257e53ee4b18\",\"878fbc71e5e0a0cb5118\",\"134d3df626b276a67275\",\"3935c67248ca140a84b7\",\"baa517e17cd210e981c4\",\"f29c19a92e0a3522510c\",\"8f93ec48430c64515362\",\"02c99f75bd3ebc4c115c\",\"2e7ba90093e1e4c0bae0\",\"28f02490bc0780da1ede\",\"72ee60533ce4970ba135\"],\"applyOnlyToTargetVisuals\":true,\"suppressData\":true}},{\"displayName\":\"D INFO TRENDS\",\"name\":\"Bookmark2e87e1691b3862077730\",\"explorationState\":{\"version\":\"1.3\",\"activeSection\":\"ReportSectionb63c0964e356021e695b\",\"sections\":{\"ReportSectionb63c0964e356021e695b\":{\"visualContainers\":{},\"visualContainerGroups\":{\"1eaaa2786b7c756951b7\":{\"isHidden\":false},\"00022aa0d3e28320a4ea\":{\"isHidden\":true},\"db663f47ca3cce960626\":{\"isHidden\":false},\"d6d2061e3a8472928e09\":{\"isHidden\":true},\"068f08d285909b5931b3\":{\"isHidden\":true},\"8320bb2036a8eee40565\":{\"isHidden\":true},\"e6b402353da657b951b1\":{\"isHidden\":false},\"0516d87aad04d462220e\":{\"isHidden\":true}}}},\"objects\":{\"merge\":{\"outspacePane\":[{\"properties\":{\"expanded\":{\"expr\":{\"Literal\":{\"Value\":\"false\"}}}}}]}}},\"options\":{\"targetVisualNames\":[\"0516d87aad04d462220e\",\"e6b402353da657b951b1\",\"8320bb2036a8eee40565\",\"0c359ecf40e85e20c940\",\"19d8b8d0257e53ee4b18\",\"878fbc71e5e0a0cb5118\",\"134d3df626b276a67275\",\"3935c67248ca140a84b7\",\"baa517e17cd210e981c4\",\"f29c19a92e0a3522510c\",\"8f93ec48430c64515362\",\"02c99f75bd3ebc4c115c\",\"2e7ba90093e1e4c0bae0\",\"28f02490bc0780da1ede\",\"72ee60533ce4970ba135\"],\"applyOnlyToTargetVisuals\":true,\"suppressData\":true}},{\"displayName\":\"D INFO ACTION\",\"name\":\"Bookmark61ad8e906bce71a0edde\",\"explorationState\":{\"version\":\"1.3\",\"activeSection\":\"ReportSectionb63c0964e356021e695b\",\"sections\":{\"ReportSectionb63c0964e356021e695b\":{\"visualContainers\":{},\"visualContainerGroups\":{\"1eaaa2786b7c756951b7\":{\"isHidden\":false},\"00022aa0d3e28320a4ea\":{\"isHidden\":true},\"db663f47ca3cce960626\":{\"isHidden\":false},\"d6d2061e3a8472928e09\":{\"isHidden\":true},\"068f08d285909b5931b3\":{\"isHidden\":true},\"8320bb2036a8eee40565\":{\"isHidden\":true},\"e6b402353da657b951b1\":{\"isHidden\":true},\"0516d87aad04d462220e\":{\"isHidden\":false}}}},\"objects\":{\"merge\":{\"outspacePane\":[{\"properties\":{\"expanded\":{\"expr\":{\"Literal\":{\"Value\":\"false\"}}}}}]}}},\"options\":{\"targetVisualNames\":[\"0516d87aad04d462220e\",\"e6b402353da657b951b1\",\"8320bb2036a8eee40565\",\"0c359ecf40e85e20c940\",\"19d8b8d0257e53ee4b18\",\"878fbc71e5e0a0cb5118\",\"134d3df626b276a67275\",\"3935c67248ca140a84b7\",\"baa517e17cd210e981c4\",\"f29c19a92e0a3522510c\",\"8f93ec48430c64515362\",\"02c99f75bd3ebc4c115c\",\"2e7ba90093e1e4c0bae0\",\"28f02490bc0780da1ede\",\"72ee60533ce4970ba135\"],\"suppressData\":true,\"applyOnlyToTargetVisuals\":true}},{\"displayName\":\"D INFO CLOSED\",\"name\":\"Bookmark36a5b2671c14bd209edd\",\"explorationState\":{\"version\":\"1.3\",\"activeSection\":\"ReportSectionb63c0964e356021e695b\",\"sections\":{\"ReportSectionb63c0964e356021e695b\":{\"visualContainers\":{},\"visualContainerGroups\":{\"1eaaa2786b7c756951b7\":{\"isHidden\":false},\"00022aa0d3e28320a4ea\":{\"isHidden\":true},\"db663f47ca3cce960626\":{\"isHidden\":false},\"d6d2061e3a8472928e09\":{\"isHidden\":true},\"068f08d285909b5931b3\":{\"isHidden\":true},\"8320bb2036a8eee40565\":{\"isHidden\":true},\"e6b402353da657b951b1\":{\"isHidden\":true},\"0516d87aad04d462220e\":{\"isHidden\":true}}}},\"objects\":{\"merge\":{\"outspacePane\":[{\"properties\":{\"expanded\":{\"expr\":{\"Literal\":{\"Value\":\"false\"}}}}}]}}},\"options\":{\"targetVisualNames\":[\"0516d87aad04d462220e\",\"e6b402353da657b951b1\",\"8320bb2036a8eee40565\",\"0c359ecf40e85e20c940\",\"19d8b8d0257e53ee4b18\",\"878fbc71e5e0a0cb5118\",\"134d3df626b276a67275\",\"3935c67248ca140a84b7\",\"baa517e17cd210e981c4\",\"f29c19a92e0a3522510c\",\"8f93ec48430c64515362\",\"02c99f75bd3ebc4c115c\",\"2e7ba90093e1e4c0bae0\",\"28f02490bc0780da1ede\",\"72ee60533ce4970ba135\"],\"applyOnlyToTargetVisuals\":true,\"suppressData\":true}}],\"defaultDrillFilterOtherVisuals\":true,\"slowDataSourceSettings\":{\"isCrossHighlightingDisabled\":false,\"isSlicerSelectionsButtonEnabled\":false,\"isFilterSelectionsButtonEnabled\":false,\"isFieldWellButtonEnabled\":false,\"isApplyAllButtonEnabled\":false},\"linguisticSchemaSyncVersion\":2,\"settings\":{\"useNewFilterPaneExperience\":true,\"allowChangeFilterTypes\":true,\"useStylableVisualContainerHeader\":true,\"exportDataMode\":1,\"useEnhancedTooltips\":true},\"objects\":{\"section\":[{\"properties\":{\"verticalAlignment\":{\"expr\":{\"Literal\":{\"Value\":\"'Top'\"}}}}}],\"outspacePane\":[{\"properties\":{\"expanded\":{\"expr\":{\"Literal\":{\"Value\":\"true\"}}}}}]}}",
  "layoutOptimization": 0,
  "resourcePackages": [
    {
      "resourcePackage": {
        "disabled": false,
        "items": [
          {
            "name": "AccessibleDefault",
            "path": "BuiltInThemes/AccessibleDefault.json",
            "type": 201
          },
          {
            "name": "CY24SU08",
            "path": "BaseThemes/CY24SU08.json",
            "type": 202
          }
        ],
        "name": "SharedResources",
        "type": 2
      }
    }
  ],
  "sections": [
    {
      "config": "{}",
      "displayName": "Page 1",
      "displayOption": 1,
      "filters": "[]",
      "height": 720.00,
      "name": "9f2d5caeb63434400e34",
      "visualContainers": [],
      "width": 1280.00
    }
  ],
  "theme": "AccessibleDefault"
}